argtoml/__init__.py
argtoml/__main__.py
argtoml/main.py
argtoml/opt.py
argtoml-0.5.10.dist-info/LICENSE
argtoml-0.5.10.dist-info/METADATA
argtoml-0.5.10.dist-info/WHEEL
argtoml-0.5.10.dist-info/top_level.txt
argtoml-0.5.10.dist-info/RECORD
