Metadata-Version: 2.2
Name: argtoml
Version: 0.5.10
Summary: Add the keys from a .toml file to your CLI as arguments. Their values default to the values in the .toml file.
Author-email: Jochem Hölscher <a.fake@e.mail>
Project-URL: homepage, https://github.com/JJJHolscher/argtoml
Classifier: Programming Language :: Python :: 3
Classifier: License :: OSI Approved :: MIT License
Classifier: Operating System :: OS Independent
Requires-Python: >=3.11
License-File: LICENSE
Requires-Dist: tomli_w
